mypreprocessinglib/__init__.py
mypreprocessinglib/categorical_encoder.py
mypreprocessinglib/data_type_converter.py
mypreprocessinglib/date_time_handler.py
mypreprocessinglib/feature_engineer.py
mypreprocessinglib/missing_value_handler.py
mypreprocessinglib/outlier_handler.py
mypreprocessinglib/scaler.py
mypreprocessinglib/test_data_preprocessing.py
mypreprocessinglib/text_cleaner.py
mypreprocessinglib-0.1.dist-info/METADATA
mypreprocessinglib-0.1.dist-info/WHEEL
mypreprocessinglib-0.1.dist-info/top_level.txt
mypreprocessinglib-0.1.dist-info/RECORD
