Metadata-Version: 2.1
Name: mypreprocessinglib
Version: 0.1
Summary: A comprehensive data preprocessing library for Python
Home-page: https://github.com/Fzehzeh/mypreprocessinglib
Author: Zehra Tonga
Author-email: tongafatmazehra@gmail.com 
Classifier: Programming Language :: Python :: 3
Classifier: License :: OSI Approved :: MIT License
Classifier: Operating System :: OS Independent
Requires-Python: >=3.6
Requires-Dist: pandas
Requires-Dist: numpy
Requires-Dist: scikit-learn
Requires-Dist: nltk
